upsp-4.2.data/data/bin/upsp-external-calibration
upsp-4.2.data/data/bin/upsp-make-processing-tree
upsp-4.2.data/data/bin/upsp-plotting
upsp-4.2.data/data/bin/upsp-kulite-comparison
upsp-4.2.data/data/bin/upsp-qsub-args
upsp-4.2.data/data/lib/libupsp_kdtree.dylib
upsp-4.2.dist-info/RECORD
upsp-4.2.dist-info/WHEEL
upsp-4.2.dist-info/top_level.txt
upsp-4.2.dist-info/LICENSE.txt
upsp-4.2.dist-info/METADATA
upsp/_version.py
upsp/__init__.py
upsp/raycast.cpython-39-darwin.so
upsp/libupsp_kdtree.dylib
upsp/video/util.py
upsp/video/__init__.py
upsp/video/mraw.py
upsp/video/cine.py
upsp/video/__main__.py
upsp/video/base.py
upsp/target_operations/blob_localization_methods.py
upsp/target_operations/target_detection.py
upsp/target_operations/__init__.py
upsp/target_operations/gaussian_localization_methods.py
upsp/target_operations/target_bumping.py
upsp/kulite_comparison/plotting.py
upsp/kulite_comparison/__init__.py
upsp/kulite_comparison/spatial_queries.py
upsp/kulite_comparison/selection.py
upsp/processing/plot3d.py
upsp/processing/tree.py
upsp/processing/grids.py
upsp/processing/io.py
upsp/processing/__init__.py
upsp/processing/p3d_utilities.py
upsp/processing/p3d_conversions.py
upsp/processing/context.py
upsp/processing/kulite_utilities.py
upsp/processing/kulite_processing.py
upsp/processing/templates/gltf-viewer.html.template
upsp/processing/templates/launcher.sh.template
upsp/processing/templates/add-field.sh.template
upsp/processing/templates/run-step-serial.sh.template
upsp/processing/templates/run-step-parallel.sh.template
upsp/.dylibs/libImath-3_1.29.8.0.dylib
upsp/intensity_mapping/__init__.py
upsp/intensity_mapping/patching.py
upsp/intensity_mapping/node_pixel_mapping.py
upsp/cam_cal_utils/external_calibrate.py
upsp/cam_cal_utils/photogrammetry.py
upsp/cam_cal_utils/__init__.py
upsp/cam_cal_utils/parsers.py
upsp/cam_cal_utils/visualization.py
upsp/cam_cal_utils/internal_calibration.py
upsp/cam_cal_utils/visibility.py
upsp/cam_cal_utils/camera_tunnel_calibrate.py
upsp/cam_cal_utils/img_utils.py
