Metadata-Version: 2.1
Name: upsp
Version: 4.2
Summary: NASA uPSP data processing applications and utilities
Author: NASA uPSP developers
License: NASA OPEN SOURCE AGREEMENT VERSION 1.3
Requires-Python: ~=3.9.0
License-File: LICENSE.txt
Requires-Dist: matplotlib
Requires-Dist: numpy
Requires-Dist: opencv-python-headless (==4.5.2.54)
Requires-Dist: pandas
Requires-Dist: scipy
Requires-Dist: shapely
